chronoscope/__init__.py
chronoscope/__main__.py
chronoscope/chart.py
chronoscope/db.py
chronoscope/drawer.py
chronoscope/hist.py
chronoscope/parser.py
chronoscope/queue.py
chronoscope/tree.py
chronoscope/utils.py
chronoscope/vcd.py
Chronoscope-0.0.4.dist-info/COPYING
Chronoscope-0.0.4.dist-info/METADATA
Chronoscope-0.0.4.dist-info/WHEEL
Chronoscope-0.0.4.dist-info/entry_points.txt
Chronoscope-0.0.4.dist-info/top_level.txt
Chronoscope-0.0.4.dist-info/RECORD
