Metadata-Version: 2.1
Name: Chronoscope
Version: 0.0.4
Summary: A cross-platform matplotlib-based observability tool
Home-page: https://github.com/just-now/chronoscope
Author: Anatoliy Bilenko
Author-email: anatoliy.bilenko@gmail.com
License: LGPLv3
Keywords: cli observability
Classifier: Development Status :: 3 - Alpha
Classifier: Environment :: Console
Classifier: Intended Audience :: Developers
Classifier: License :: OSI Approved :: GNU Lesser General Public License v3 (LGPLv3)
Classifier: Operating System :: OS Independent
Classifier: Programming Language :: Python :: 3
Classifier: Programming Language :: Python :: 3.10
Classifier: Programming Language :: Python :: 3.11
Classifier: Programming Language :: Python :: 3.12
Classifier: Topic :: System :: Monitoring
Requires-Python: >=3.10
License-File: COPYING
Requires-Dist: peewee
Requires-Dist: matplotlib
Requires-Dist: PyYAML
Requires-Dist: graphviz
Requires-Dist: packaging
Requires-Dist: scipy
Requires-Dist: pyvcd
